fishpi/__fishpi__.py
fishpi/__init__.py
fishpi/__version__.py
fishpi/chatroom.py
fishpi/emoji.py
fishpi/notice.py
fishpi/user.py
fishpi-0.2.1.dist-info/LICENSE
fishpi-0.2.1.dist-info/METADATA
fishpi-0.2.1.dist-info/WHEEL
fishpi-0.2.1.dist-info/top_level.txt
fishpi-0.2.1.dist-info/RECORD
