Metadata-Version: 2.1
Name: fishpi
Version: 0.2.1
Summary: Package used to Call All FishPi API.
Home-page: https://github.com/FishPiOffical/fishpi.py
Author: Hancel.Lin
Author-email: imlinhanchao@gmail.com
License: MIT
Classifier: License :: OSI Approved :: MIT License
Classifier: Programming Language :: Python
Classifier: Programming Language :: Python :: 3
Classifier: Programming Language :: Python :: 3.6
Classifier: Programming Language :: Python :: Implementation :: CPython
Classifier: Programming Language :: Python :: Implementation :: PyPy
Requires-Python: >=3.6.0
License-File: LICENSE
Requires-Dist: rel
Requires-Dist: requests
Requires-Dist: websocket-client
